setup.py
fabctx/__init__.py
fabctx/ctx.py
fabctx/http.py
fabctx/virtualenv.py
fabctx.egg-info/.DS_Store
fabctx.egg-info/PKG-INFO
fabctx.egg-info/SOURCES.txt
fabctx.egg-info/dependency_links.txt
fabctx.egg-info/not-zip-safe
fabctx.egg-info/requires.txt
fabctx.egg-info/top_level.txt