Metadata-Version: 1.1
Name: fabctx
Version: 0.0.3
Summary: 
